qedma_api/__init__.py
qedma_api/clients/__init__.py
qedma_api/clients/base_client.py
qedma_api/clients/client.py
qedma_api/exceptions.py
qedma_api/helpers.py
qedma_api/models.py
qedma_api/pauli_utils.py
qedma_api/py.typed
qedma_api-0.19.7.dist-info/METADATA
qedma_api-0.19.7.dist-info/WHEEL
qedma_api-0.19.7.dist-info/RECORD
