Metadata-Version: 2.4
Name: qedma-api
Version: 0.19.7
Summary: Qedma QESEM SDK
Author: Qedma Support
Author-email: support@qedma.com
Requires-Python: >=3.10,<3.14
Classifier: Operating System :: MacOS
Classifier: Operating System :: Microsoft :: Windows
Classifier: Operating System :: POSIX
Classifier: Operating System :: Unix
Classifier: Programming Language :: Python
Classifier: Programming Language :: Python :: 3
Classifier: Programming Language :: Python :: 3.10
Classifier: Programming Language :: Python :: 3.11
Classifier: Programming Language :: Python :: 3.12
Classifier: Programming Language :: Python :: 3.13
Classifier: Typing :: Typed
Requires-Dist: loguru (>=0.7.2,<0.8.0)
Requires-Dist: pydantic (>=2.9)
Requires-Dist: qiskit (>=1.0.2,<3.0.0)
Requires-Dist: qiskit-qasm3-import (>=0.5.1,<0.6.0)
Requires-Dist: requests (>=2.32.3,<3.0.0)
Requires-Dist: tenacity (==9.1.2)
Requires-Dist: typing-extensions (>=4.12.2,<5.0.0)
Project-URL: documentation, https://docs.qedma.io/
Project-URL: download, https://pypi.org/project/qedma-api/#files
Project-URL: homepage, https://www.qedma.com/
Project-URL: release notes, https://docs.qedma.io/release_notes/
